evalstack/__init__.py
evalstack/_modidx.py
evalstack/readers.py
evalstack-0.0.2.dist-info/licenses/LICENSE
evalstack-0.0.2.dist-info/METADATA
evalstack-0.0.2.dist-info/WHEEL
evalstack-0.0.2.dist-info/entry_points.txt
evalstack-0.0.2.dist-info/top_level.txt
evalstack-0.0.2.dist-info/RECORD
